LICENSE.txt
README.md
setup.py
stockly/__init__.py
stockly/stockly_common.py
stockly.egg-info/PKG-INFO
stockly.egg-info/SOURCES.txt
stockly.egg-info/dependency_links.txt
stockly.egg-info/requires.txt
stockly.egg-info/top_level.txt
tests/test_stockly_common.py