Metadata-Version: 2.1
Name: stockly
Version: 0.0.1
Summary: All useful common functions
Home-page: https://gitlab.com/mahendra210/python-package
Author: Mahendra Bhanage
Author-email: mbhanage@woyce.io
License: MIT
Keywords: stockly
License-File: LICENSE.txt
